crawlMpGui/__init__.py
crawlMpGui/resources/__init__.py
crawlMpGui/resources/arrow-right.png
crawlMpGui/resources/done.png
crawlMpGui/resources/loading.gif
crawlMpGui/resources/reset.png
crawlMpGui/resources/resources.qrc
crawlMpGui/scripts/__init__.py
crawlMpGui/widgets/__init__.py
crawlMpGui/widgets/results_view.py
crawlMpGui/widgets/results_widget.py
crawlMpGui-0.0.9.data/scripts/search_fs_mp_gui
crawlMpGui-0.0.9.dist-info/LICENSE
crawlMpGui-0.0.9.dist-info/METADATA
crawlMpGui-0.0.9.dist-info/WHEEL
crawlMpGui-0.0.9.dist-info/top_level.txt
crawlMpGui-0.0.9.dist-info/RECORD
