Metadata-Version: 2.1
Name: crawlMpGui
Version: 0.0.9
Summary: GUI for CrawlMp
Home-page: https://github.com/domarm-comat/crawlMpGui
Author: Martin Domaracký
Author-email: domarm@comat.sk
License: MIT
Platform: UNKNOWN
Classifier: Programming Language :: Python :: 3
Classifier: Operating System :: OS Independent
Classifier: Topic :: Software Development :: Libraries
Classifier: License :: OSI Approved :: MIT License
Classifier: Natural Language :: English
Classifier: Intended Audience :: Science/Research
Requires-Python: >=3.7
License-File: LICENSE
Requires-Dist: crawlMp (>=0.3.7)
Requires-Dist: PyQt6 (>=6.2.2)
